pytntprog/__init__.py
pytntprog/args.py
pytntprog/pytntprog.py
pytntprog/update.py
pytntprog-2.0.1.dist-info/METADATA
pytntprog-2.0.1.dist-info/WHEEL
pytntprog-2.0.1.dist-info/entry_points.txt
pytntprog-2.0.1.dist-info/top_level.txt
pytntprog-2.0.1.dist-info/RECORD
