Metadata-Version: 2.4
Name: pytntprog
Version: 2.0.1
Summary: pytntprog displays the program of tnt tv in France
Home-page: https://github.com/thib1984/pytntprog
Author: thib1984
Author-email: thibault.garcon@gmail.com
License: MIT
Classifier: Programming Language :: Python :: 3.6
Classifier: Programming Language :: Python :: 3.7
Classifier: Programming Language :: Python :: 3.8
Classifier: Programming Language :: Python :: 3.9
Classifier: Programming Language :: Python :: 3.10
Classifier: Programming Language :: Python :: 3.11
Classifier: Programming Language :: Python :: 3.12
Classifier: License :: OSI Approved :: MIT License
Classifier: Operating System :: OS Independent
Requires-Python: >=3.6
Requires-Dist: colorama
Requires-Dist: termcolor
Requires-Dist: columnar
Requires-Dist: requests
Requires-Dist: py7zr
Dynamic: author
Dynamic: author-email
Dynamic: classifier
Dynamic: description
Dynamic: home-page
Dynamic: license
Dynamic: requires-dist
Dynamic: requires-python
Dynamic: summary
